pythttp/AdminPanel.py
pythttp/Log_Manager.py
pythttp/Protocol.py
pythttp/RequestHandler.py
pythttp/ServerDashboard.py
pythttp/Structure.py
pythttp/Thread_Manager.py
pythttp/__init__.py
pythttp-0.2.1.dist-info/METADATA
pythttp-0.2.1.dist-info/WHEEL
pythttp-0.2.1.dist-info/top_level.txt
pythttp-0.2.1.dist-info/RECORD
