Metadata-Version: 2.1
Name: pythttp
Version: 0.2.1
Summary: A small example package
Home-page: https://github.com/projectlonginus/httpy
Author: Example Author
Author-email: Longinus <team.longinus.project@gmail.com>
Project-URL: Homepage, https://github.com/projectlonginus/httpy
Project-URL: Bug Tracker, https://github.com/projectlonginus/httpy/issues
Classifier: Programming Language :: Python :: 3
Requires-Python: >=3.11
Requires-Dist: dataclasses
Requires-Dist: datetime
Requires-Dist: uuid
